{
    "formatVersion": 1,
    "name": "authlib-injector",
    "uid": "moe.yushi.authlibinjector",
    "versions": [
        {
            "recommended": false,
            "releaseTime": "2023-07-29T00:07:12.981360+00:00",
            "sha256": "a97d4cc23f4377c214772ccde2145f545a9ac1ebf4b93d1a0e0dce6c872d2f7e",
            "type": "release",
            "version": "1.0.1-4405964"
        },
        {
            "recommended": false,
            "releaseTime": "2023-07-29T00:07:12.981054+00:00",
            "sha256": "44a3b5d30ce833637bf34a291710485f2fd0bc420b617a34a252463a6aed9722",
            "type": "release",
            "version": "1.0.2-e47b187"
        },
        {
            "recommended": false,
            "releaseTime": "2023-07-29T00:07:12.980762+00:00",
            "sha256": "366581b59b34ba7db0d0332b4968339cd717dab932bdb50b74c1084867955df0",
            "type": "release",
            "version": "1.0.3-3185f73"
        },
        {
            "recommended": false,
            "releaseTime": "2023-07-29T00:07:12.980413+00:00",
            "sha256": "48b0db37985db9fc6b2a04f77b6365088f88ef462257188d2a9715cddc72e875",
            "type": "release",
            "version": "1.0.4-014eb57"
        },
        {
            "recommended": false,
            "releaseTime": "2023-07-29T00:07:12.980127+00:00",
            "sha256": "a107da7c20c829de76b533dee05f85cc06b58432f7d2aa94f3624244fd1984d0",
            "type": "release",
            "version": "1.0.6-28fcbd2"
        },
        {
            "recommended": false,
            "releaseTime": "2023-07-29T00:07:12.979849+00:00",
            "sha256": "64e76fec2fed210f5693cf539b6374d1fece9a5309026e37ae112ea794b3408a",
            "type": "release",
            "version": "1.0.7-5015962"
        },
        {
            "recommended": false,
            "releaseTime": "2023-07-29T00:07:12.979566+00:00",
            "sha256": "b964685e5df7dbc960578f2c5fe7e325888fc088ad7dbf70c0b15d34de724131",
            "type": "release",
            "version": "1.0.8-feab914"
        },
        {
            "recommended": false,
            "releaseTime": "2023-07-29T00:07:12.979288+00:00",
            "sha256": "73bbd52f832f7013628e8068a3a6248285f81a5db9159211128c4e474fef5678",
            "type": "release",
            "version": "1.0.9-1731f0b"
        },
        {
            "recommended": false,
            "releaseTime": "2023-07-29T00:07:12.979009+00:00",
            "sha256": "4b04a9f8fbfa6845d2921e3f8b6310dc2992ca5d30821537ec856b5981013e36",
            "type": "release",
            "version": "1.0.10-8aa3f20"
        },
        {
            "recommended": false,
            "releaseTime": "2023-07-29T00:07:12.978732+00:00",
            "sha256": "e93ef59fe5d890a8c3cbc1a5713c7acefd5b5f16dbe7fd4f32a384b50889463d",
            "type": "release",
            "version": "1.1.11-bfa2629"
        },
        {
            "recommended": false,
            "releaseTime": "2023-07-29T00:07:12.978453+00:00",
            "sha256": "3779e5054af7da96aaa65fb5505762cd78c1a965ca299697a8a66090a6da5a0d",
            "type": "release",
            "version": "1.1.12-83dcd83"
        },
        {
            "recommended": false,
            "releaseTime": "2023-07-29T00:07:12.978174+00:00",
            "sha256": "9a85456587eae27cde311cc2627311de374616e9771abb7affeead954fc047aa",
            "type": "release",
            "version": "1.1.13-c7866c1"
        },
        {
            "recommended": false,
            "releaseTime": "2023-07-29T00:07:12.977895+00:00",
            "sha256": "1c722d9fcc01e3d2f062363d09ef24516ab59cb2cf6a94993db88bbf44ede331",
            "type": "release",
            "version": "1.1.14-7710506"
        },
        {
            "recommended": false,
            "releaseTime": "2023-07-29T00:07:12.977616+00:00",
            "sha256": "9defcc52861a382e6c8c63b7b15bdc973b3e9cde24875fe39b0fb64c885baa8e",
            "type": "release",
            "version": "1.1.15-11c952d"
        },
        {
            "recommended": false,
            "releaseTime": "2023-07-29T00:07:12.977337+00:00",
            "sha256": "7b902d74789c716925bc749ad1555ea87f98fec9befdab86855dfc3b64fab1b9",
            "type": "release",
            "version": "1.1.16-f460e0e"
        },
        {
            "recommended": false,
            "releaseTime": "2023-07-29T00:07:12.977057+00:00",
            "sha256": "b1a8070917d21d005d66341ed69bd731998d658609735271d42d2f2d0c8a0bdf",
            "type": "release",
            "version": "1.1.17-4b3b0be"
        },
        {
            "recommended": false,
            "releaseTime": "2023-07-29T00:07:12.976769+00:00",
            "sha256": "4ea81adff37217680d062742da45e911efae6df90eacb1f6d7f669eed6c0daca",
            "type": "release",
            "version": "1.1.18-daa6fb4"
        },
        {
            "recommended": false,
            "releaseTime": "2023-07-29T00:07:12.976424+00:00",
            "sha256": "24175b88582ed6f43c65ed5488f806f1625b7563b8394efbed832c2ed7c7d2d4",
            "type": "release",
            "version": "1.1.19-36fc21d"
        },
        {
            "recommended": false,
            "releaseTime": "2023-07-29T00:07:12.976136+00:00",
            "sha256": "706b64cad02b897e7aad7de2458d48c49e598e2e2298f4c6eac83abc71587881",
            "type": "release",
            "version": "1.1.20-940a3d5"
        },
        {
            "recommended": false,
            "releaseTime": "2023-07-29T00:07:12.975851+00:00",
            "sha256": "3d500e9ed8417151366340b9ff612038b2fb4cc2428b6e9175500702ab15ced4",
            "type": "release",
            "version": "1.1.21-f242b97"
        },
        {
            "recommended": false,
            "releaseTime": "2023-07-29T00:07:12.975566+00:00",
            "sha256": "11bd8ec46bc5f2e5060da361a1ff7e9fbf0634a850607e723e23d2b7f75d911f",
            "type": "release",
            "version": "1.1.22-69c4067"
        },
        {
            "recommended": false,
            "releaseTime": "2023-07-29T00:07:12.975274+00:00",
            "sha256": "3439d2b7f2b499ea8920de3278a50903a9353f9a29b9b56c6111af5fc7376b25",
            "type": "release",
            "version": "1.1.23-209ba0e"
        },
        {
            "recommended": false,
            "releaseTime": "2023-07-29T00:07:12.974962+00:00",
            "sha256": "38926876331d69d1ae27df35670f4afbf291950e7a8074d6137e5e75acb59839",
            "type": "release",
            "version": "1.1.24-fe7cb0b"
        },
        {
            "recommended": false,
            "releaseTime": "2023-07-29T00:07:12.973594+00:00",
            "sha256": "c0d39f02d5e3ce4fc245dd64283d6b567be41490cfeacc0d407df347af2fa403",
            "type": "release",
            "version": "1.1.25-37e97b1"
        },
        {
            "recommended": false,
            "releaseTime": "2023-07-29T00:07:12.973312+00:00",
            "sha256": "5c01986f70fe7e44192661a7fc4dec90234572fe4d6bb56740fdda90ecdb046a",
            "type": "release",
            "version": "1.1.26-41a7a47"
        },
        {
            "recommended": false,
            "releaseTime": "2023-07-29T00:07:12.973025+00:00",
            "sha256": "76b4c39ff46cf6dd5857e0344b82137c2bedfefaa60a36e2dbc3eb09031f70fe",
            "type": "release",
            "version": "1.1.27-5ef5f8e"
        },
        {
            "recommended": false,
            "releaseTime": "2023-07-29T00:07:12.972732+00:00",
            "sha256": "72bf537c5aaf3aa14079db477c6c8b3d68be1fd5fd725575db48c239fcbaca0b",
            "type": "release",
            "version": "1.1.28-682ecc6"
        },
        {
            "recommended": false,
            "releaseTime": "2023-07-29T00:07:12.972425+00:00",
            "sha256": "e523adae5160bbe82e2da059482f24968d722f9cd6ed3f23a9fdc89bd5737dfc",
            "type": "release",
            "version": "1.1.29"
        },
        {
            "recommended": false,
            "releaseTime": "2023-07-29T00:07:12.972138+00:00",
            "sha256": "abdfddba7d8dc9def826546022f5794c272fca6edf42f1f4b922da5ecdde2fa7",
            "type": "release",
            "version": "1.1.30"
        },
        {
            "recommended": false,
            "releaseTime": "2023-07-29T00:07:12.971853+00:00",
            "sha256": "b3ba8468185c8634c3a9c8e0efbd105829c1aea0ff5f4a7ecb5aa3a75b9a1ca6",
            "type": "release",
            "version": "1.1.31"
        },
        {
            "recommended": false,
            "releaseTime": "2023-07-29T00:07:12.971560+00:00",
            "sha256": "594f8951b0eb200c4934dfeca79d814bac7d5fc7ca16bdda16790a5b3e47f8a0",
            "type": "release",
            "version": "1.1.32"
        },
        {
            "recommended": false,
            "releaseTime": "2023-07-29T00:07:12.971271+00:00",
            "sha256": "97e5d4f434dcfd72af0cd448531cf2942530ea620dcac93bbd1772896ded226a",
            "type": "release",
            "version": "1.1.33"
        },
        {
            "recommended": false,
            "releaseTime": "2023-07-29T00:07:12.970991+00:00",
            "sha256": "eef3e35588306de6cfed7ae4c3e78eab6046fa20a34060e9d3ba9e2d22d3ded3",
            "type": "release",
            "version": "1.1.34"
        },
        {
            "recommended": false,
            "releaseTime": "2023-07-29T00:07:12.970710+00:00",
            "sha256": "ce7d3628a9e2c6f651706969cccc6c3d9d001051c5d44a631a551cf0d0c45d3b",
            "type": "release",
            "version": "1.1.35"
        },
        {
            "recommended": false,
            "releaseTime": "2023-07-29T00:07:12.970427+00:00",
            "sha256": "bb8ae87afd7659fc7c2612e1cd406e6a09f11907629a3fa06d53494b733556c6",
            "type": "release",
            "version": "1.1.36"
        },
        {
            "recommended": false,
            "releaseTime": "2023-07-29T00:07:12.970149+00:00",
            "sha256": "c7b6163d57a946eed67d46c49eb432a3c494ddf8a92070b4ce096a56d2468fdb",
            "type": "release",
            "version": "1.1.37"
        },
        {
            "recommended": false,
            "releaseTime": "2023-07-29T00:07:12.969863+00:00",
            "sha256": "2f6cfdaf2f036a4533e1e48788a606bec7d2483dd51a86079d51ba8e8e2776d9",
            "type": "release",
            "version": "1.1.38"
        },
        {
            "recommended": false,
            "releaseTime": "2023-07-29T00:07:12.969583+00:00",
            "sha256": "61cfc8d6b5c536604a7e518d3fd02eaed6868fecb124b9b724950bae0831b686",
            "type": "release",
            "version": "1.1.39"
        },
        {
            "recommended": false,
            "releaseTime": "2023-07-29T00:07:12.969292+00:00",
            "sha256": "3e22241dcc63573dc8165b595e31b49e4b17e8ff679ccb906376c081634a30ac",
            "type": "release",
            "version": "1.1.40"
        },
        {
            "recommended": false,
            "releaseTime": "2023-07-29T00:07:12.969009+00:00",
            "sha256": "fde37a5986f5919d73938ec8a00eb05e5b4c6ed4a66dda380327c930be5219c9",
            "type": "release",
            "version": "1.1.41"
        },
        {
            "recommended": false,
            "releaseTime": "2023-07-29T00:07:12.968716+00:00",
            "sha256": "4256bd28e867d2f9a7b49f209403dc8bfda6ffce59b32f1f96383d7fa3a61c12",
            "type": "release",
            "version": "1.1.42"
        },
        {
            "recommended": false,
            "releaseTime": "2023-07-29T00:07:12.968390+00:00",
            "sha256": "365b2d7d0b8c9bde2def15e466f3d69513863585a7361075f4bbe135d656a678",
            "type": "release",
            "version": "1.1.43"
        },
        {
            "recommended": false,
            "releaseTime": "2023-07-29T00:07:12.968101+00:00",
            "sha256": "85e1608f433296479a5ea812559f389b66371758c7534acc74d0875c259295f0",
            "type": "release",
            "version": "1.1.44"
        },
        {
            "recommended": false,
            "releaseTime": "2023-07-29T00:07:12.967807+00:00",
            "sha256": "f40b3351c7b1df30e8e197d35aceea1f80f22f078a553e401ca43228df1bbf8a",
            "type": "release",
            "version": "1.1.45"
        },
        {
            "recommended": false,
            "releaseTime": "2023-07-29T00:07:12.967422+00:00",
            "sha256": "c6105af1a755fa982ad74e41826e1818dacb94a9dc9d833b2d0776e25548ea00",
            "type": "release",
            "version": "1.1.46"
        },
        {
            "recommended": false,
            "releaseTime": "2023-07-29T00:07:12.967128+00:00",
            "sha256": "74eba2deebb74d5de028980fcbb1fcdca614156d1f98845b36b8407a078fcc73",
            "type": "release",
            "version": "1.1.47"
        },
        {
            "recommended": false,
            "releaseTime": "2023-07-29T00:07:12.966830+00:00",
            "sha256": "4286c0d70895e184ea1a73758beb3c2bc70a1ac68e37c65087366b2e1eb58331",
            "type": "release",
            "version": "1.2.0"
        },
        {
            "recommended": false,
            "releaseTime": "2023-07-29T00:07:12.966521+00:00",
            "sha256": "f7b3143366c64f419ef7a3fbb778accc212af9e5da3e17067f270b8564f2043f",
            "type": "release",
            "version": "1.2.1"
        },
        {
            "recommended": false,
            "releaseTime": "2023-07-29T00:07:12.966177+00:00",
            "sha256": "e0607d3cd168d5b505c3d9acbee818e5a933773f2f2b680281e2bd1eac3a9ab5",
            "type": "release",
            "version": "1.2.2"
        },
        {
            "recommended": true,
            "releaseTime": "2023-07-29T00:07:12.965626+00:00",
            "sha256": "f44cd87e0619d9f7f7575bd9b442cfbbc904a73b1fe41e2db3be2a6a5c8115c7",
            "type": "release",
            "version": "1.2.3"
        }
    ]
}